zope/sendmail/README.rst
zope/sendmail/__init__.py
zope/sendmail/configure.zcml
zope/sendmail/delivery.py
zope/sendmail/interfaces.py
zope/sendmail/maildir.py
zope/sendmail/mailer.py
zope/sendmail/meta.zcml
zope/sendmail/queue.py
zope/sendmail/vocabulary.py
zope/sendmail/zcml.py
zope/sendmail/tests/__init__.py
zope/sendmail/tests/mail.zcml
zope/sendmail/tests/test_delivery.py
zope/sendmail/tests/test_directives.py
zope/sendmail/tests/test_maildir.py
zope/sendmail/tests/test_mailer.py
zope/sendmail/tests/test_queue.py
zope/sendmail/tests/test_vocabulary.py
zope_sendmail-7.0.dist-info/licenses/LICENSE.txt
zope_sendmail-7.0.dist-info/METADATA
zope_sendmail-7.0.dist-info/WHEEL
zope_sendmail-7.0.dist-info/entry_points.txt
zope_sendmail-7.0.dist-info/top_level.txt
zope_sendmail-7.0.dist-info/RECORD
